CHANGELOG.md
LICENSE
MANIFEST.in
README.md
setup.py
sample-scripts/calc-sample1.py
sample-scripts/pdf-convert-sample1.py
sample-scripts/sample.csv
sample-scripts/writer-sample1.py
sample-scripts/datadir/data1.csv
unotools/__init__.py
unotools/context.py
unotools/datatypes.py
unotools/errors.py
unotools/unohelper.py
unotools/utils.py
unotools.egg-info/PKG-INFO
unotools.egg-info/SOURCES.txt
unotools.egg-info/dependency_links.txt
unotools.egg-info/requires.txt
unotools.egg-info/top_level.txt
unotools/component/__init__.py
unotools/component/calc.py
unotools/component/writer.py
unotools/data/__init__.py
unotools/data/csv.py