Metadata-Version: 1.1
Name: unotools
Version: 0.3.3
Summary: Interacting with OpenOffice.org/LibreOffice using UNO
Home-page: http://bitbucket.org/t2y/unotools
Author: Tetsuya Morimoto
Author-email: tetsuya dot morimoto at gmail dot com
License: Apache License 2.0
Keywords: uno,pyuno,office,OOo
Platform: unix
Platform: linux
Platform: osx
Classifier: License :: OSI Approved :: Apache Software License
Classifier: Development Status :: 4 - Beta
Classifier: Intended Audience :: Developers
Classifier: Operating System :: MacOS :: MacOS X
Classifier: Operating System :: POSIX
Classifier: Programming Language :: Python :: 3
Classifier: Programming Language :: Python :: 3.3
Classifier: Programming Language :: Python :: 3.4
Classifier: Programming Language :: Python :: 3 :: Only
Classifier: Programming Language :: Python :: Implementation :: CPython
Classifier: Topic :: Software Development
Classifier: Topic :: Software Development :: Libraries
Classifier: Topic :: Office/Business :: Office Suites
